accountkitlogin/__init__.py
accountkitlogin/apps.py
accountkitlogin/authenticate.py
accountkitlogin/tests.py
accountkitlogin/views.py
accountkitlogin/templatetags/__init__.py
accountkitlogin/templatetags/accountkit.py
django_accountkit-0.2.3.dist-info/LICENSE
django_accountkit-0.2.3.dist-info/METADATA
django_accountkit-0.2.3.dist-info/WHEEL
django_accountkit-0.2.3.dist-info/top_level.txt
django_accountkit-0.2.3.dist-info/RECORD
