Metadata-Version: 2.1
Name: django-accountkit
Version: 0.2.3
Summary: Facebook accountkit support for Django
Home-page: https://github.com/antiproblemist/django-accountkit
Author: Shahzeb Qureshi
Author-email: shahzeb_iam@outlook.com
License: MIT
Platform: UNKNOWN
Classifier: Development Status :: 4 - Beta
Classifier: Environment :: Console
Classifier: Environment :: Web Environment
Classifier: Intended Audience :: Developers
Classifier: Intended Audience :: System Administrators
Classifier: Programming Language :: Python :: 3.7
Classifier: Programming Language :: Python :: 2.7
Classifier: Programming Language :: Python :: 3
Classifier: Programming Language :: Python :: 3.4
Classifier: Programming Language :: Python :: 3.5
Classifier: Programming Language :: Python :: 3.6
Classifier: Topic :: Software Development
Requires-Dist: Django (>=1.11)
Requires-Dist: requests (>=2.18.4)
